srswti_universal_three/__init__.py
srswti_universal_three/api.py
srswti_universal_three/home.py
srswti_universal_three/llm.py
srswti_universal_three/main.py
srswti_universal_three/models.py
srswti_universal_three/signup.py
srswti_universal_three/speech.py
srswti_universal_three/stt_socket.py
srswti_universal_three/utils.py
srswti_universal_three/helpers/__init__.py
srswti_universal_three/helpers/chat_history_manager.py
srswti_universal_three/helpers/node_manager.py
srswti_universal_three/helpers/profiler.py
srswti_universal_three/helpers/quick_one.py
srswti_universal_three/helpers/redis_server.py
srswti_universal_three/helpers/response_gen_v2.py
srswti_universal_three/helpers/shared.py
srswti_universal_three/helpers/stt.py
srswti_universal_three/helpers/tts.py
srswti_universal_three/helpers/tts_fastapi.py
srswti_universal_three-1.0.1.dist-info/METADATA
srswti_universal_three-1.0.1.dist-info/WHEEL
srswti_universal_three-1.0.1.dist-info/RECORD
