Metadata-Version: 2.4
Name: srswti-universal-three
Version: 1.0.1
Project-URL: Homepage, https://www.srswti.com/
Author-email: SRSWTI - Knowledge and Inference Platform <team@srswti.com>
Classifier: Development Status :: 3 - Alpha
Classifier: Environment :: Console
Classifier: Intended Audience :: Developers
Classifier: Intended Audience :: Education
Classifier: Intended Audience :: Information Technology
Classifier: Intended Audience :: Science/Research
Classifier: License :: OSI Approved :: MIT License
Classifier: Natural Language :: English
Classifier: Operating System :: OS Independent
Classifier: Programming Language :: Python :: 3
Classifier: Programming Language :: Python :: 3.7
Classifier: Programming Language :: Python :: 3.8
Classifier: Programming Language :: Python :: 3.9
Classifier: Programming Language :: Python :: 3.10
Classifier: Programming Language :: Python :: 3.11
Classifier: Topic :: Scientific/Engineering :: Artificial Intelligence
Classifier: Topic :: Scientific/Engineering :: Information Analysis
Classifier: Topic :: Software Development :: Libraries :: Application Frameworks
Classifier: Topic :: Software Development :: Libraries :: Python Modules
Classifier: Topic :: Text Processing :: General
Classifier: Topic :: Text Processing :: Linguistic
Requires-Python: >=3.9
Requires-Dist: anthropic
Requires-Dist: cerebras-cloud-sdk
Requires-Dist: fastapi
Requires-Dist: gcloud
Requires-Dist: google-ai-generativelanguage
Requires-Dist: google-api-core
Requires-Dist: google-api-python-client
Requires-Dist: google-auth
Requires-Dist: google-auth-httplib2
Requires-Dist: google-cloud-speech
Requires-Dist: google-cloud-texttospeech
Requires-Dist: google-genai
Requires-Dist: google-generativeai
Requires-Dist: googleapis-common-protos
Requires-Dist: grpcio
Requires-Dist: httpx
Requires-Dist: jiter
Requires-Dist: lxml
Requires-Dist: nltk
Requires-Dist: oauth2client
Requires-Dist: openai
Requires-Dist: packaging
Requires-Dist: pillow
Requires-Dist: postgrest
Requires-Dist: pyaudio
Requires-Dist: pydantic
Requires-Dist: pydantic-core
Requires-Dist: pydub
Requires-Dist: pyinstaller
Requires-Dist: python-dotenv
Requires-Dist: redis
Requires-Dist: regex
Requires-Dist: requests
Requires-Dist: starlette
Requires-Dist: supabase
Requires-Dist: tqdm
Requires-Dist: uvicorn
Requires-Dist: websockets
Provides-Extra: all
Requires-Dist: easyocr; extra == 'all'
Provides-Extra: dev
Requires-Dist: black; extra == 'dev'
Requires-Dist: flake8; extra == 'dev'
Requires-Dist: isort; extra == 'dev'
Requires-Dist: pytest; extra == 'dev'
Requires-Dist: twine; extra == 'dev'
Provides-Extra: docs
Requires-Dist: sphinx; extra == 'docs'
Requires-Dist: sphinx-rtd-theme; extra == 'docs'
